{
    "LECTURER_001": {
        "tutor_id": "LECTURER_001",
        "slots": [
            {
                "id": 202,
                "start": "2025-12-01T18:00:00Z",
                "end": "2025-12-01T23:30:00Z"
            },
            {
                "id": 203,
                "start": "2025-11-06T12:39:00Z",
                "end": "2025-11-06T15:44:00Z"
            }
        ]
    },
    "LECTURER_002": {
        "tutor_id": "LECTURER_002",
        "slots": [
            {
                "id": 201,
                "start": "2025-12-01T11:00:00Z",
                "end": "2025-12-01T12:00:00Z"
            }
        ]
    }
}